sa_app/__init__.py
sa_app/app.py
sa_app/common/__init__.py
sa_app/common/utils.py
sa_app/data/__init__.py
sa_app/data/data.py
sa_app/data/data_cleaner.py
sa_app/data/kaggle_dataset.py
sa_app/inference/__init__.py
sa_app/inference/inference.py
sa_app/inference_app.py
sa_app/models/__init__.py
sa_app/models/model.py
sa_app/training/__init__.py
sa_app/training/lightning_model_wrapper.py
sa_app/training/optmizer.py
sa_app-1.0.9.dist-info/METADATA
sa_app-1.0.9.dist-info/WHEEL
sa_app-1.0.9.dist-info/RECORD
