Metadata-Version: 2.1
Name: sa_app
Version: 1.0.9
Summary: Sentiment analyzer app
Author: prabhu
Author-email: prabhupad26@gmail.com
Requires-Python: >=3.10,<4.0
Classifier: License :: OSI Approved :: MIT License
Classifier: Operating System :: OS Independent
Classifier: Programming Language :: Python :: 3
Classifier: Programming Language :: Python :: 3.10
Classifier: Programming Language :: Python :: 3.11
Classifier: Programming Language :: Python :: 3.12
Requires-Dist: flask (>=2.3.2,<3.0.0)
Requires-Dist: nltk (>=3.8.1,<4.0.0)
Requires-Dist: pandas (>=2.2.3,<3.0.0)
Requires-Dist: pytest
Requires-Dist: pytorch-lightning (==2.0.4)
Requires-Dist: spacy (==3.7.6)
Requires-Dist: thinc (==8.2.5)
Requires-Dist: torch (>=2.2.0,<3.0.0)
Requires-Dist: transformers (>=4.45.1,<5.0.0)
Requires-Dist: wandb (>=0.18.1,<0.19.0)
